CHANGES.txt
COPYRIGHT.txt
LICENSE.txt
README.txt
bootstrap.py
buildout.cfg
setup.py
src/gocept/__init__.py
src/gocept.cxoracle.egg-info/PKG-INFO
src/gocept.cxoracle.egg-info/SOURCES.txt
src/gocept.cxoracle.egg-info/dependency_links.txt
src/gocept.cxoracle.egg-info/entry_points.txt
src/gocept.cxoracle.egg-info/namespace_packages.txt
src/gocept.cxoracle.egg-info/requires.txt
src/gocept.cxoracle.egg-info/top_level.txt
src/gocept/cxoracle/README.txt
src/gocept/cxoracle/__init__.py
src/gocept/cxoracle/basiclite-darwin.zip
src/gocept/cxoracle/basiclite-linux.zip
src/gocept/cxoracle/loader.c
src/gocept/cxoracle/recipe.py
src/gocept/cxoracle/sdk-darwin.zip
src/gocept/cxoracle/sdk-linux.zip
src/gocept/cxoracle/tests.py