Metadata-Version: 1.0
Name: gocept.cxoracle
Version: 0.1
Summary: zc.buildout recipe for installing cx_Oracle
Home-page: http://pypi.python.org/pypi/gocept.cxoracle
Author: Christian Zagrodnick
Author-email: cz@gocept.com
License: ZPL 2.1
Download-URL: http://pypi.python.org/pypi/gocept.cxoracle
Platform: UNKNOWN
Classifier: Development Status :: 3 - Alpha
Classifier: Environment :: Console
Classifier: Environment :: Plugins
Classifier: Framework :: Buildout
Classifier: Intended Audience :: Developers
Classifier: License :: OSI Approved :: Zope Public License
Classifier: Operating System :: MacOS :: MacOS X
Classifier: Operating System :: POSIX :: Linux
Classifier: Programming Language :: C
Classifier: Programming Language :: Python
Classifier: Topic :: Software Development :: Build Tools
Classifier: Topic :: System :: Software Distribution
